silico/__init__.py
silico/__main__.py
silico/analysis.py
silico/base.py
silico/cli.py
silico/common.py
silico/cui.py
silico/metrics.py
silico/ml.py
silico/plot.py
silico/urinal.py
silico-0.3.0.dist-info/LICENSE.txt
silico-0.3.0.dist-info/METADATA
silico-0.3.0.dist-info/WHEEL
silico-0.3.0.dist-info/entry_points.txt
silico-0.3.0.dist-info/top_level.txt
silico-0.3.0.dist-info/RECORD
