Metadata-Version: 2.1
Name: silico
Version: 0.3.0
Summary: Python package to handle in silico experiments
Home-page: https://github.com/Dih5/silico
Author: Dih5
Author-email: dihedralfive@gmail.com
Classifier: Development Status :: 3 - Alpha
Classifier: Intended Audience :: Science/Research
Classifier: License :: OSI Approved :: MIT License
Classifier: Natural Language :: English
Classifier: Programming Language :: Python :: 3
Classifier: Programming Language :: Python :: 3.5
Classifier: Programming Language :: Python :: 3.6
Classifier: Programming Language :: Python :: 3.7
Classifier: Programming Language :: Python :: 3.8
Classifier: Programming Language :: Python :: 3.9
Classifier: Programming Language :: Python :: 3.10
License-File: LICENSE.txt
Requires-Dist: numpy
Requires-Dist: pandas
Requires-Dist: scipy
Requires-Dist: scikit-learn
Requires-Dist: click
Requires-Dist: tqdm
Provides-Extra: docs
Requires-Dist: nbsphinx ; extra == 'docs'
Requires-Dist: sphinx-rtd-theme ; extra == 'docs'
Requires-Dist: IPython ; extra == 'docs'
Provides-Extra: progress
Requires-Dist: tqdm ; extra == 'progress'
Provides-Extra: test
Requires-Dist: pytest ; extra == 'test'
